dataql/__init__.py
dataql/resources.py
dataql/exceptions.py
dataql/utils.py
dataql/solvers/registry.py
dataql/solvers/__init__.py
dataql/solvers/resources.py
dataql/solvers/filters.py
dataql/solvers/base.py
dataql/solvers/exceptions.py
dataql/solvers/django/__init__.py
dataql/solvers/django/naive.py
dataql/solvers/django/__pycache__/naive.cpython-34.pyc
dataql/solvers/django/__pycache__/__init__.cpython-34.pyc
dataql/solvers/__pycache__/exceptions.cpython-34.pyc
dataql/solvers/__pycache__/registry.cpython-34.pyc
dataql/solvers/__pycache__/__init__.cpython-34.pyc
dataql/solvers/__pycache__/base.cpython-34.pyc
dataql/parsers/mixins.py
dataql/parsers/__init__.py
dataql/parsers/base.py
dataql/parsers/generic.py
dataql/parsers/exceptions.py
dataql/parsers/__pycache__/mixins.cpython-34.pyc
dataql/parsers/__pycache__/generic.cpython-34.pyc
dataql/parsers/__pycache__/__init__.cpython-34.pyc
dataql/parsers/__pycache__/base.cpython-34.pyc
dataql/__pycache__/resources.cpython-34.pyc
dataql/__pycache__/utils.cpython-34.pyc
dataql/__pycache__/__init__.cpython-34.pyc
dataql-0.1.4.dist-info/DESCRIPTION.rst
dataql-0.1.4.dist-info/RECORD
dataql-0.1.4.dist-info/top_level.txt
dataql-0.1.4.dist-info/metadata.json
dataql-0.1.4.dist-info/WHEEL
dataql-0.1.4.dist-info/METADATA
