Metadata-Version: 2.0
Name: dataql
Version: 0.1.4
Summary: ``dataql`` is for "Data Query Language". It allows to query data in a simple way.
Home-page: https://github.com/twidi/py-dataql
Author: Stephane "Twidi" Angel
Author-email: s.angel@twidi.com
License: BSD
Platform: UNKNOWN
Classifier: Development Status :: 4 - Beta
Classifier: Operating System :: OS Independent
Classifier: Intended Audience :: Developers
Classifier: License :: OSI Approved :: BSD License
Classifier: Programming Language :: Python :: 3
Classifier: Programming Language :: Python :: 3.4
Classifier: Topic :: Software Development :: Libraries
Classifier: Topic :: Software Development :: Libraries :: Python Modules
Requires-Dist: parsimonious (==0.6.2)
